{"version":1,"resource":"vscode-userdata:/c%3A/Users/ao/Desktop/monokon_release/monokon/VSCode-win32-x64-1.118.1/data/user-data/User/keybindings.json","entries":[{"id":"OkRA.json","timestamp":1777905374499},{"id":"tplb.json","timestamp":1777905787465},{"id":"QHbF.json","timestamp":1777905912149},{"id":"t5b2.json","timestamp":1777906169564},{"id":"vYUk.json","timestamp":1777906191670},{"id":"tpVF.json","timestamp":1777906375158},{"id":"uFDi.json","timestamp":1777906416302},{"id":"q5le.json","timestamp":1777906734857}]}